pygwan/__init__.py
pygwan/pygwan.py
pygwan-0.2.9.dist-info/METADATA
pygwan-0.2.9.dist-info/WHEEL
pygwan-0.2.9.dist-info/licenses/LICENSE
pygwan-0.2.9.dist-info/RECORD
