Metadata-Version: 2.4
Name: pygwan
Version: 0.2.9
Summary: WhatsApp Cloud API is complicated, Twilio is expensive, PyGwan is the opposite of both. Free & Intuitive! ~ Tarmica Chiwara.
Project-URL: Repository, https://github.com/lordskyzw/pygwan
Author-email: Tarmica Chiwara <tarimicac@gmail.com>
License: MIT
License-File: LICENSE
Keywords: api,chatbot,messaging,opensource,whatsapp
Classifier: License :: OSI Approved :: MIT License
Classifier: Operating System :: OS Independent
Classifier: Programming Language :: Python :: 3
Requires-Python: >=3.7
Requires-Dist: colorama>=0.4.3
Requires-Dist: requests-toolbelt>=0.9.1
Requires-Dist: requests>=2.25.0
